{
    "OTROS PREMIOS:": "",
    "Associació amics del corpus:": "",
    "": "",
    "29": "1",
    "Per unes falles neutres y sostenibles:": "",
    "21": "6",
    "211": "1",
    "99": "3",
    "80": "4",
    "318": "5",
    "PREMIOS FALLAS EXPERIMENTALES FALLAS 2024:": "",
    "302": "2",
    "143": "3",
    "66": "4",
    "240": "5",
    "226": "7",
    "30": "8",
    "236": "9",
    "52": "5",
    "PREMIOS CALIU FALLAS GRANDES 2024:": "",
    "384": "1",
    "39": "2",
    "305": "3",
    "319": "4"
}